hm_pyhelper/__init__.py
hm_pyhelper/constants/__init__.py
hm_pyhelper/constants/diagnostics.py
hm_pyhelper/constants/nebra.py
hm_pyhelper/constants/shipping.py
hm_pyhelper/diagnostics/__init__.py
hm_pyhelper/diagnostics/diagnostic.py
hm_pyhelper/diagnostics/diagnostics_report.py
hm_pyhelper/exceptions.py
hm_pyhelper/gateway_grpc/__init__.py
hm_pyhelper/gateway_grpc/client.py
hm_pyhelper/gateway_grpc/exceptions.py
hm_pyhelper/gateway_mfr
hm_pyhelper/gateway_mfr_aarch64
hm_pyhelper/gateway_mfr_x86_64
hm_pyhelper/hardware_definitions.py
hm_pyhelper/lock_singleton.py
hm_pyhelper/logger.py
hm_pyhelper/main.py
hm_pyhelper/miner_json_rpc/__init__.py
hm_pyhelper/miner_json_rpc/client.py
hm_pyhelper/miner_json_rpc/exceptions.py
hm_pyhelper/miner_param.py
hm_pyhelper/protos/__init__.py
hm_pyhelper/protos/blockchain_txn_add_gateway_v1_pb2.py
hm_pyhelper/protos/blockchain_txn_pb2.py
hm_pyhelper/protos/gateway_staking_mode_pb2.py
hm_pyhelper/protos/local_pb2.py
hm_pyhelper/protos/local_pb2_grpc.py
hm_pyhelper/protos/region_pb2.py
hm_pyhelper/sbc.py
hm_pyhelper/tests/__init__.py
hm_pyhelper/tests/data/sentry/sample_exception_event.json
hm_pyhelper/tests/data/sentry/sample_logging_event.json
hm_pyhelper/tests/data/sentry/sample_logging_hints.json
hm_pyhelper/tests/test_diagnostic_report.py
hm_pyhelper/tests/test_gateway_grpc.py
hm_pyhelper/tests/test_get_mac_address.py
hm_pyhelper/tests/test_hardware_definitions.py
hm_pyhelper/tests/test_lock_singleton.py
hm_pyhelper/tests/test_logger.py
hm_pyhelper/tests/test_miner_json_rpc.py
hm_pyhelper/tests/test_miner_param.py
hm_pyhelper/tests/test_sbc.py
hm_pyhelper/tests/test_util_pgp.py
hm_pyhelper/tests/test_util_sentry.py
hm_pyhelper/util/__init__.py
hm_pyhelper/util/pgp.py
hm_pyhelper/util/sentry.py
hm_pyhelper-0.14.38.dist-info/LICENSE
hm_pyhelper-0.14.38.dist-info/METADATA
hm_pyhelper-0.14.38.dist-info/WHEEL
hm_pyhelper-0.14.38.dist-info/RECORD
