Metadata-Version: 2.1
Name: hm-pyhelper
Version: 0.14.38
Summary: Helium Python Helper
Author: Nebra Ltd
Author-email: support@nebra.com
Requires-Python: >=3.9,<4.0
Classifier: Programming Language :: Python :: 3
Classifier: Programming Language :: Python :: 3.9
Classifier: Programming Language :: Python :: 3.10
Classifier: Programming Language :: Python :: 3.11
Requires-Dist: base58 (>=2.1.1,<2.2.0)
Requires-Dist: grpcio (>=1.50.1,<2.0.0)
Requires-Dist: packaging (>=23.1,<23.2)
Requires-Dist: protobuf (>=4.23.4,<4.24.0)
Requires-Dist: requests (>=2.32.2,<2.33.0)
Requires-Dist: retry (>=0.9.2,<0.10.0)
